[
  {
    "id": "u_rahim",
    "name": "Rahim",
    "email": "rahim@example.com",
    "avatar": "/avatars/rahim.png",
    "provider": "google"
  },
  {
    "id": "u_sadia",
    "name": "Sadia",
    "email": "sadia@example.com",
    "avatar": "/avatars/sadia.png",
    "provider": "github"
  },
  {
    "id": "u_tanvir",
    "name": "Tanvir",
    "email": "tanvir@example.com",
    "avatar": "/avatars/tanvir.png",
    "provider": "google"
  },
  {
    "id": "u_asif",
    "name": "Asif",
    "email": "asif@example.com",
    "avatar": "/avatars/asif.png",
    "provider": "google"
  },
  {
    "id": "u_smrity",
    "name": "Smrity",
    "email": "smrity@example.com",
    "avatar": "/avatars/smrity.png",
    "provider": "google"
  }
]
